{
  "updated_at": "2026-05-01T03:00:22",
  "groups": [
    {
      "group_name": "Super Lig ",
      "table": [
        {
          "position": 1,
          "team": {
            "id": "645",
            "name": "Galatasaray"
          },
          "played": 31,
          "win": 23,
          "draw": 5,
          "loss": 3,
          "goal_for": 72,
          "goal_against": 23,
          "goal_difference": 49,
          "points": 74
        },
        {
          "position": 2,
          "team": {
            "id": "611",
            "name": "Fenerbahçe"
          },
          "played": 31,
          "win": 19,
          "draw": 10,
          "loss": 2,
          "goal_for": 68,
          "goal_against": 33,
          "goal_difference": 35,
          "points": 67
        },
        {
          "position": 3,
          "team": {
            "id": "998",
            "name": "Trabzonspor"
          },
          "played": 31,
          "win": 19,
          "draw": 8,
          "loss": 4,
          "goal_for": 58,
          "goal_against": 34,
          "goal_difference": 24,
          "points": 65
        },
        {
          "position": 4,
          "team": {
            "id": "549",
            "name": "Beşiktaş"
          },
          "played": 31,
          "win": 16,
          "draw": 8,
          "loss": 7,
          "goal_for": 54,
          "goal_against": 36,
          "goal_difference": 18,
          "points": 56
        },
        {
          "position": 5,
          "team": {
            "id": "564",
            "name": "Başakşehir"
          },
          "played": 31,
          "win": 14,
          "draw": 9,
          "loss": 8,
          "goal_for": 52,
          "goal_against": 31,
          "goal_difference": 21,
          "points": 51
        },
        {
          "position": 6,
          "team": {
            "id": "994",
            "name": "Göztepe"
          },
          "played": 31,
          "win": 13,
          "draw": 12,
          "loss": 6,
          "goal_for": 39,
          "goal_against": 27,
          "goal_difference": 12,
          "points": 51
        },
        {
          "position": 7,
          "team": {
            "id": "3603",
            "name": "Samsunspor"
          },
          "played": 31,
          "win": 11,
          "draw": 12,
          "loss": 8,
          "goal_for": 39,
          "goal_against": 41,
          "goal_difference": -2,
          "points": 45
        },
        {
          "position": 8,
          "team": {
            "id": "607",
            "name": "Konyaspor"
          },
          "played": 31,
          "win": 10,
          "draw": 10,
          "loss": 11,
          "goal_for": 40,
          "goal_against": 42,
          "goal_difference": -2,
          "points": 40
        },
        {
          "position": 9,
          "team": {
            "id": "1007",
            "name": "Rizespor"
          },
          "played": 31,
          "win": 9,
          "draw": 10,
          "loss": 12,
          "goal_for": 41,
          "goal_against": 44,
          "goal_difference": -3,
          "points": 37
        },
        {
          "position": 10,
          "team": {
            "id": "3573",
            "name": "Gaziantep FK"
          },
          "played": 31,
          "win": 9,
          "draw": 10,
          "loss": 12,
          "goal_for": 41,
          "goal_against": 52,
          "goal_difference": -11,
          "points": 37
        },
        {
          "position": 11,
          "team": {
            "id": "7411",
            "name": "Kocaelispor"
          },
          "played": 31,
          "win": 9,
          "draw": 9,
          "loss": 13,
          "goal_for": 25,
          "goal_against": 35,
          "goal_difference": -10,
          "points": 36
        },
        {
          "position": 12,
          "team": {
            "id": "996",
            "name": "Alanyaspor"
          },
          "played": 31,
          "win": 6,
          "draw": 15,
          "loss": 10,
          "goal_for": 37,
          "goal_against": 38,
          "goal_difference": -1,
          "points": 33
        },
        {
          "position": 13,
          "team": {
            "id": "1004",
            "name": "Kasımpaşa"
          },
          "played": 31,
          "win": 7,
          "draw": 10,
          "loss": 14,
          "goal_for": 29,
          "goal_against": 45,
          "goal_difference": -16,
          "points": 31
        },
        {
          "position": 14,
          "team": {
            "id": "997",
            "name": "Gençlerbirliği S.K."
          },
          "played": 31,
          "win": 7,
          "draw": 7,
          "loss": 17,
          "goal_for": 30,
          "goal_against": 44,
          "goal_difference": -14,
          "points": 28
        },
        {
          "position": 15,
          "team": {
            "id": "3588",
            "name": "Eyüpspor"
          },
          "played": 31,
          "win": 7,
          "draw": 7,
          "loss": 17,
          "goal_for": 25,
          "goal_against": 44,
          "goal_difference": -19,
          "points": 28
        },
        {
          "position": 16,
          "team": {
            "id": "1005",
            "name": "Antalyaspor"
          },
          "played": 31,
          "win": 7,
          "draw": 7,
          "loss": 17,
          "goal_for": 30,
          "goal_against": 51,
          "goal_difference": -21,
          "points": 28
        },
        {
          "position": 17,
          "team": {
            "id": "1001",
            "name": "Kayserispor"
          },
          "played": 31,
          "win": 5,
          "draw": 11,
          "loss": 15,
          "goal_for": 23,
          "goal_against": 57,
          "goal_difference": -34,
          "points": 26
        },
        {
          "position": 18,
          "team": {
            "id": "3589",
            "name": "Fatih Karagümrük"
          },
          "played": 31,
          "win": 5,
          "draw": 6,
          "loss": 20,
          "goal_for": 27,
          "goal_against": 53,
          "goal_difference": -26,
          "points": 21
        }
      ]
    },
    {
      "group_name": "Lig A",
      "table": [
        {
          "position": 1,
          "team": {
            "id": "3583",
            "name": "BB Bodrumspor"
          },
          "played": 8,
          "win": 5,
          "draw": 2,
          "loss": 1,
          "goal_for": 19,
          "goal_against": 8,
          "goal_difference": 11,
          "points": 17
        },
        {
          "position": 3,
          "team": {
            "id": "3601",
            "name": "Pendikspor"
          },
          "played": 8,
          "win": 4,
          "draw": 3,
          "loss": 1,
          "goal_for": 15,
          "goal_against": 8,
          "goal_difference": 7,
          "points": 15
        },
        {
          "position": 11,
          "team": {
            "id": "3578",
            "name": "İstanbulspor"
          },
          "played": 8,
          "win": 2,
          "draw": 5,
          "loss": 1,
          "goal_for": 10,
          "goal_against": 9,
          "goal_difference": 1,
          "points": 11
        },
        {
          "position": 14,
          "team": {
            "id": "1002",
            "name": "Sivasspor"
          },
          "played": 7,
          "win": 2,
          "draw": 2,
          "loss": 3,
          "goal_for": 10,
          "goal_against": 9,
          "goal_difference": 1,
          "points": 8
        },
        {
          "position": 18,
          "team": {
            "id": "3575",
            "name": "Hatayspor"
          },
          "played": 8,
          "win": 0,
          "draw": 3,
          "loss": 5,
          "goal_for": 9,
          "goal_against": 20,
          "goal_difference": -11,
          "points": 3
        },
        {
          "position": 20,
          "team": {
            "id": "3563",
            "name": "Adana Demirspor"
          },
          "played": 7,
          "win": 0,
          "draw": 1,
          "loss": 6,
          "goal_for": 4,
          "goal_against": 28,
          "goal_difference": -24,
          "points": 0
        }
      ]
    }
  ]
}